__init__.py
main.py
ndpprep/__init__.py
ndpprep/cli/__init__.py
ndpprep/cli/main.py
ndpprep/cli/settings.py
ndpprep/decryption/__init__.py
ndpprep/decryption/main.py
ndpprep/encryption/__init__.py
ndpprep/encryption/main.py
ndpprep/inventory/__init__.py
ndpprep/inventory/main.py
ndpprep/masked/__init__.py
ndpprep/masked/main.py
ndpprep/process_data/__init__.py
ndpprep/process_data/main.py
ndpprep/save_sftp/__init__.py
ndpprep/save_sftp/main.py
ndpprep/secret_key/__init__.py
ndpprep/secret_key/main.py
ndpprep/shp_file/__init__.py
ndpprep/shp_file/main.py
ndpprep/shp_file/mygeospatial.py
ndpprep/target_schema/__init__.py
ndpprep/target_schema/granite.py
ndpprep/target_schema/neps.py
ndpprep/target_schema/nis.py
ndpprep/unmask/__init__.py
ndpprep/unmask/main.py
ndpprep-0.0.8.dist-info/METADATA
ndpprep-0.0.8.dist-info/WHEEL
ndpprep-0.0.8.dist-info/entry_points.txt
ndpprep-0.0.8.dist-info/top_level.txt
ndpprep-0.0.8.dist-info/RECORD
