Metadata-Version: 2.1
Name: ndpprep
Version: 0.0.8
Summary: A command line tool to prepare high-quality data in Parquet
Author-email: Mohd Zaid Waqiyuddin Mohd Zulkifli <zaidwaqi@gmail.com>
License: MIT
Project-URL: Homepage, https://github.com/zaidwaqi/ndpprep
Project-URL: Issues, https://github.com/pypa/zaidwaqi/ndpprep/issues
Classifier: Programming Language :: Python :: 3
Classifier: License :: OSI Approved :: MIT License
Classifier: Operating System :: OS Independent
Requires-Python: >=3.11
Requires-Dist: pyarrow >=14.0.0
Requires-Dist: Click
Requires-Dist: pandas
Requires-Dist: geopandas
Requires-Dist: paramiko
